splunk_hec/__init__.py
splunk_hec_ftf-1.0.3.dist-info/LICENSE
splunk_hec_ftf-1.0.3.dist-info/METADATA
splunk_hec_ftf-1.0.3.dist-info/WHEEL
splunk_hec_ftf-1.0.3.dist-info/top_level.txt
splunk_hec_ftf-1.0.3.dist-info/RECORD
