Metadata-Version: 2.1
Name: splunk-hec-ftf
Version: 1.0.3
Summary: A library for sending data to the Splunk HTTP Event Collector.
Author-email: John Landers <support@fromthefuture.net>
Project-URL: Homepage, https://gitlab.com/johnfromthefuture/splunk-hec-library/
Project-URL: Bug Tracker, https://gitlab.com/johnfromthefuture/splunk-hec-library/-/issues
Classifier: Programming Language :: Python :: 3
Classifier: Development Status :: 5 - Production/Stable
Classifier: License :: OSI Approved :: GNU General Public License v3 (GPLv3)
Classifier: Natural Language :: English
Classifier: Operating System :: OS Independent
Requires-Python: >=3.6
License-File: LICENSE
